stat_01/__init__.py
stat_01/common.py
stat_01/map.py
stat_01/stat_01.py
stat_01-0.4.0.dist-info/LICENSE
stat_01-0.4.0.dist-info/METADATA
stat_01-0.4.0.dist-info/WHEEL
stat_01-0.4.0.dist-info/entry_points.txt
stat_01-0.4.0.dist-info/top_level.txt
stat_01-0.4.0.dist-info/RECORD
